{"title":"我的微信连三界","url":"https://cn.baozimh.com/comic/wodeweixinliansanjie-iciyuandongman","favicon":"https://cn.baozimh.com/favicon.ico","elements":[{"title":"第453话 杀了岛主之子！","contents":"<a href=\"/user/page_direct?comic_id=wodeweixinliansanjie-iciyuandongman&amp;section_slot=0&amp;chapter_slot=455\" rel=\"noreferrer\" class=\"comics-chapters__item\" data-v-9a7b0fc8=\"\"><div style=\"flex: 1;\" data-v-9a7b0fc8=\"\"><span data-v-9a7b0fc8=\"\">第453话 杀了岛主之子！</span></div></a>","link":"https://cn.baozimh.com/user/page_direct?comic_id=wodeweixinliansanjie-iciyuandongman&section_slot=0&chapter_slot=455","retrieved":1636220454865},{"title":"第452话 他可以越级战斗","contents":"<a href=\"/user/page_direct?comic_id=wodeweixinliansanjie-iciyuandongman&amp;section_slot=0&amp;chapter_slot=454\" rel=\"noreferrer\" class=\"comics-chapters__item\" data-v-9a7b0fc8=\"\"><div style=\"flex: 1;\" data-v-9a7b0fc8=\"\"><span data-v-9a7b0fc8=\"\">第452话 他可以越级战斗</span></div></a>","link":"https://cn.baozimh.com/user/page_direct?comic_id=wodeweixinliansanjie-iciyuandongman&section_slot=0&chapter_slot=454","retrieved":1635906208707},{"title":"第451话 白家追来了！","contents":"<a href=\"/user/page_direct?comic_id=wodeweixinliansanjie-iciyuandongman&amp;section_slot=0&amp;chapter_slot=453\" rel=\"noreferrer\" class=\"comics-chapters__item\" data-v-9a7b0fc8=\"\"><div style=\"flex: 1;\" data-v-9a7b0fc8=\"\"><span data-v-9a7b0fc8=\"\">第451话 白家追来了！</span></div></a>","link":"https://cn.baozimh.com/user/page_direct?comic_id=wodeweixinliansanjie-iciyuandongman&section_slot=0&chapter_slot=453","retrieved":1635914322632},{"title":"第450话 我林海从没怕过谁","contents":"<a href=\"/user/page_direct?comic_id=wodeweixinliansanjie-iciyuandongman&amp;section_slot=0&amp;chapter_slot=452\" rel=\"noreferrer\" class=\"comics-chapters__item\" data-v-9a7b0fc8=\"\"><div style=\"flex: 1;\" data-v-9a7b0fc8=\"\"><span data-v-9a7b0fc8=\"\">第450话 我林海从没怕过谁</span></div></a>","link":"https://cn.baozimh.com/user/page_direct?comic_id=wodeweixinliansanjie-iciyuandongman&section_slot=0&chapter_slot=452","retrieved":1635914322632},{"title":"第449话 我说，你是个人渣！","contents":"<a href=\"/user/page_direct?comic_id=wodeweixinliansanjie-iciyuandongman&amp;section_slot=0&amp;chapter_slot=451\" rel=\"noreferrer\" class=\"comics-chapters__item\" data-v-9a7b0fc8=\"\"><div style=\"flex: 1;\" data-v-9a7b0fc8=\"\"><span data-v-9a7b0fc8=\"\">第449话 我说，你是个人渣！</span></div></a>","link":"https://cn.baozimh.com/user/page_direct?comic_id=wodeweixinliansanjie-iciyuandongman&section_slot=0&chapter_slot=451","retrieved":1635914322632},{"title":"第448话 到了玉城主家门口","contents":"<a href=\"/user/page_direct?comic_id=wodeweixinliansanjie-iciyuandongman&amp;section_slot=0&amp;chapter_slot=450\" rel=\"noreferrer\" class=\"comics-chapters__item\" data-v-9a7b0fc8=\"\"><div style=\"flex: 1;\" data-v-9a7b0fc8=\"\"><span data-v-9a7b0fc8=\"\">第448话 到了玉城主家门口</span></div></a>","link":"https://cn.baozimh.com/user/page_direct?comic_id=wodeweixinliansanjie-iciyuandongman&section_slot=0&chapter_slot=450","retrieved":1635914322632},{"title":"第447话 双料超极品天赋","contents":"<a href=\"/user/page_direct?comic_id=wodeweixinliansanjie-iciyuandongman&amp;section_slot=0&amp;chapter_slot=449\" rel=\"noreferrer\" class=\"comics-chapters__item\" data-v-9a7b0fc8=\"\"><div style=\"flex: 1;\" data-v-9a7b0fc8=\"\"><span data-v-9a7b0fc8=\"\">第447话 双料超极品天赋</span></div></a>","link":"https://cn.baozimh.com/user/page_direct?comic_id=wodeweixinliansanjie-iciyuandongman&section_slot=0&chapter_slot=449","retrieved":1635914322632},{"title":"第446话 外岛的宝藏","contents":"<a href=\"/user/page_direct?comic_id=wodeweixinliansanjie-iciyuandongman&amp;section_slot=0&amp;chapter_slot=448\" rel=\"noreferrer\" class=\"comics-chapters__item\" data-v-9a7b0fc8=\"\"><div style=\"flex: 1;\" data-v-9a7b0fc8=\"\"><span data-v-9a7b0fc8=\"\">第446话 外岛的宝藏</span></div></a>","link":"https://cn.baozimh.com/user/page_direct?comic_id=wodeweixinliansanjie-iciyuandongman&section_slot=0&chapter_slot=448","retrieved":1635914322633},{"title":"第445话 领悟火之道","contents":"<a href=\"/user/page_direct?comic_id=wodeweixinliansanjie-iciyuandongman&amp;section_slot=0&amp;chapter_slot=447\" rel=\"noreferrer\" class=\"comics-chapters__item\" data-v-9a7b0fc8=\"\"><div style=\"flex: 1;\" data-v-9a7b0fc8=\"\"><span data-v-9a7b0fc8=\"\">第445话 领悟火之道</span></div></a>","link":"https://cn.baozimh.com/user/page_direct?comic_id=wodeweixinliansanjie-iciyuandongman&section_slot=0&chapter_slot=447","retrieved":1635914322633},{"title":"第444话 用阵法困住岛主","contents":"<a href=\"/user/page_direct?comic_id=wodeweixinliansanjie-iciyuandongman&amp;section_slot=0&amp;chapter_slot=446\" rel=\"noreferrer\" class=\"comics-chapters__item\" data-v-9a7b0fc8=\"\"><div style=\"flex: 1;\" data-v-9a7b0fc8=\"\"><span data-v-9a7b0fc8=\"\">第444话 用阵法困住岛主</span></div></a>","link":"https://cn.baozimh.com/user/page_direct?comic_id=wodeweixinliansanjie-iciyuandongman&section_slot=0&chapter_slot=446","retrieved":1635914322633},{"title":"第443话 玉城主逃家？","contents":"<a href=\"/user/page_direct?comic_id=wodeweixinliansanjie-iciyuandongman&amp;section_slot=0&amp;chapter_slot=445\" rel=\"noreferrer\" class=\"comics-chapters__item\" data-v-9a7b0fc8=\"\"><div style=\"flex: 1;\" data-v-9a7b0fc8=\"\"><span data-v-9a7b0fc8=\"\">第443话 玉城主逃家？</span></div></a>","link":"https://cn.baozimh.com/user/page_direct?comic_id=wodeweixinliansanjie-iciyuandongman&section_slot=0&chapter_slot=445","retrieved":1635914322633},{"title":"第442话 原来他就是岛主","contents":"<a href=\"/user/page_direct?comic_id=wodeweixinliansanjie-iciyuandongman&amp;section_slot=0&amp;chapter_slot=444\" rel=\"noreferrer\" class=\"comics-chapters__item\" data-v-9a7b0fc8=\"\"><div style=\"flex: 1;\" data-v-9a7b0fc8=\"\"><span data-v-9a7b0fc8=\"\">第442话 原来他就是岛主</span></div></a>","link":"https://cn.baozimh.com/user/page_direct?comic_id=wodeweixinliansanjie-iciyuandongman&section_slot=0&chapter_slot=444","retrieved":1635914322633},{"title":"第441话 出发，中心城！","contents":"<a href=\"/user/page_direct?comic_id=wodeweixinliansanjie-iciyuandongman&amp;section_slot=0&amp;chapter_slot=443\" rel=\"noreferrer\" class=\"comics-chapters__item\" data-v-9a7b0fc8=\"\"><div style=\"flex: 1;\" data-v-9a7b0fc8=\"\"><span data-v-9a7b0fc8=\"\">第441话 出发，中心城！</span></div></a>","link":"https://cn.baozimh.com/user/page_direct?comic_id=wodeweixinliansanjie-iciyuandongman&section_slot=0&chapter_slot=443","retrieved":1635914322633},{"title":"第440话 我连熊大都打不过了？","contents":"<a href=\"/user/page_direct?comic_id=wodeweixinliansanjie-iciyuandongman&amp;section_slot=0&amp;chapter_slot=442\" rel=\"noreferrer\" class=\"comics-chapters__item\" data-v-9a7b0fc8=\"\"><div style=\"flex: 1;\" data-v-9a7b0fc8=\"\"><span data-v-9a7b0fc8=\"\">第440话 我连熊大都打不过了？</span></div></a>","link":"https://cn.baozimh.com/user/page_direct?comic_id=wodeweixinliansanjie-iciyuandongman&section_slot=0&chapter_slot=442","retrieved":1635914322633},{"title":"第439话 领悟了道行","contents":"<a href=\"/user/page_direct?comic_id=wodeweixinliansanjie-iciyuandongman&amp;section_slot=0&amp;chapter_slot=441\" rel=\"noreferrer\" class=\"comics-chapters__item\" data-v-9a7b0fc8=\"\"><div style=\"flex: 1;\" data-v-9a7b0fc8=\"\"><span data-v-9a7b0fc8=\"\">第439话 领悟了道行</span></div></a>","link":"https://cn.baozimh.com/user/page_direct?comic_id=wodeweixinliansanjie-iciyuandongman&section_slot=0&chapter_slot=441","retrieved":1635914322633},{"title":"第438话 把心魔王关进小黑屋","contents":"<a href=\"/user/page_direct?comic_id=wodeweixinliansanjie-iciyuandongman&amp;section_slot=0&amp;chapter_slot=440\" rel=\"noreferrer\" class=\"comics-chapters__item\" data-v-9a7b0fc8=\"\"><div style=\"flex: 1;\" data-v-9a7b0fc8=\"\"><span data-v-9a7b0fc8=\"\">第438话 把心魔王关进小黑屋</span></div></a>","link":"https://cn.baozimh.com/user/page_direct?comic_id=wodeweixinliansanjie-iciyuandongman&section_slot=0&chapter_slot=440","retrieved":1635914322633},{"title":"第437话 陷入自己的“心魔”","contents":"<a href=\"/user/page_direct?comic_id=wodeweixinliansanjie-iciyuandongman&amp;section_slot=0&amp;chapter_slot=439\" rel=\"noreferrer\" class=\"comics-chapters__item\" data-v-9a7b0fc8=\"\"><div style=\"flex: 1;\" data-v-9a7b0fc8=\"\"><span data-v-9a7b0fc8=\"\">第437话 陷入自己的“心魔”</span></div></a>","link":"https://cn.baozimh.com/user/page_direct?comic_id=wodeweixinliansanjie-iciyuandongman&section_slot=0&chapter_slot=439","retrieved":1635914322633},{"title":"第436话 流沙金甲","contents":"<a href=\"/user/page_direct?comic_id=wodeweixinliansanjie-iciyuandongman&amp;section_slot=0&amp;chapter_slot=438\" rel=\"noreferrer\" class=\"comics-chapters__item\" data-v-9a7b0fc8=\"\"><div style=\"flex: 1;\" data-v-9a7b0fc8=\"\"><span data-v-9a7b0fc8=\"\">第436话 流沙金甲</span></div></a>","link":"https://cn.baozimh.com/user/page_direct?comic_id=wodeweixinliansanjie-iciyuandongman&section_slot=0&chapter_slot=438","retrieved":1635914322633},{"title":"第435话 神通卷珠帘","contents":"<a href=\"/user/page_direct?comic_id=wodeweixinliansanjie-iciyuandongman&amp;section_slot=0&amp;chapter_slot=437\" rel=\"noreferrer\" class=\"comics-chapters__item\" data-v-9a7b0fc8=\"\"><div style=\"flex: 1;\" data-v-9a7b0fc8=\"\"><span data-v-9a7b0fc8=\"\">第435话 神通卷珠帘</span></div></a>","link":"https://cn.baozimh.com/user/page_direct?comic_id=wodeweixinliansanjie-iciyuandongman&section_slot=0&chapter_slot=437","retrieved":1635914322634},{"title":"第434话 看我沙里淘金！","contents":"<a href=\"/user/page_direct?comic_id=wodeweixinliansanjie-iciyuandongman&amp;section_slot=0&amp;chapter_slot=436\" rel=\"noreferrer\" class=\"comics-chapters__item\" data-v-9a7b0fc8=\"\"><div style=\"flex: 1;\" data-v-9a7b0fc8=\"\"><span data-v-9a7b0fc8=\"\">第434话 看我沙里淘金！</span></div></a>","link":"https://cn.baozimh.com/user/page_direct?comic_id=wodeweixinliansanjie-iciyuandongman&section_slot=0&chapter_slot=436","retrieved":1635914322635},{"title":"第433话 居然被反将一军","contents":"<a href=\"/user/page_direct?comic_id=wodeweixinliansanjie-iciyuandongman&amp;section_slot=0&amp;chapter_slot=435\" rel=\"noreferrer\" class=\"comics-chapters__item\" data-v-9a7b0fc8=\"\"><div style=\"flex: 1;\" data-v-9a7b0fc8=\"\"><span data-v-9a7b0fc8=\"\">第433话 居然被反将一军</span></div></a>","link":"https://cn.baozimh.com/user/page_direct?comic_id=wodeweixinliansanjie-iciyuandongman&section_slot=0&chapter_slot=435","retrieved":1635914322637},{"title":"第432话 引敌入阵","contents":"<a href=\"/user/page_direct?comic_id=wodeweixinliansanjie-iciyuandongman&amp;section_slot=0&amp;chapter_slot=434\" rel=\"noreferrer\" class=\"comics-chapters__item\" data-v-9a7b0fc8=\"\"><div style=\"flex: 1;\" data-v-9a7b0fc8=\"\"><span data-v-9a7b0fc8=\"\">第432话 引敌入阵</span></div></a>","link":"https://cn.baozimh.com/user/page_direct?comic_id=wodeweixinliansanjie-iciyuandongman&section_slot=0&chapter_slot=434","retrieved":1635914322638},{"title":"第431话 强劲的主城城主","contents":"<a href=\"/user/page_direct?comic_id=wodeweixinliansanjie-iciyuandongman&amp;section_slot=0&amp;chapter_slot=433\" rel=\"noreferrer\" class=\"comics-chapters__item\" data-v-9a7b0fc8=\"\"><div style=\"flex: 1;\" data-v-9a7b0fc8=\"\"><span data-v-9a7b0fc8=\"\">第431话 强劲的主城城主</span></div></a>","link":"https://cn.baozimh.com/user/page_direct?comic_id=wodeweixinliansanjie-iciyuandongman&section_slot=0&chapter_slot=433","retrieved":1635914322640},{"title":"第430话 精魂疗养","contents":"<a href=\"/user/page_direct?comic_id=wodeweixinliansanjie-iciyuandongman&amp;section_slot=0&amp;chapter_slot=432\" rel=\"noreferrer\" class=\"comics-chapters__item\" data-v-9a7b0fc8=\"\"><div style=\"flex: 1;\" data-v-9a7b0fc8=\"\"><span data-v-9a7b0fc8=\"\">第430话 精魂疗养</span></div></a>","link":"https://cn.baozimh.com/user/page_direct?comic_id=wodeweixinliansanjie-iciyuandongman&section_slot=0&chapter_slot=432","retrieved":1635914322641}]}