{"title":"最强反套路系统","url":"https://cn.baozimh.com/comic/zuiqiangfantaoluxitong-chuyingshe","favicon":"https://cn.baozimh.com/favicon.ico","elements":[{"title":"567众生平等","contents":"<a href=\"/user/page_direct?comic_id=zuiqiangfantaoluxitong-chuyingshe&amp;section_slot=0&amp;chapter_slot=571\" rel=\"noreferrer\" class=\"comics-chapters__item\" data-v-9a7b0fc8=\"\"><div style=\"flex: 1;\" data-v-9a7b0fc8=\"\"><span data-v-9a7b0fc8=\"\">567众生平等</span></div></a>","link":"https://cn.baozimh.com/user/page_direct?comic_id=zuiqiangfantaoluxitong-chuyingshe&section_slot=0&chapter_slot=571","retrieved":1646660249178},{"title":"566我徐缺舍己为人！","contents":"<a href=\"/user/page_direct?comic_id=zuiqiangfantaoluxitong-chuyingshe&amp;section_slot=0&amp;chapter_slot=570\" rel=\"noreferrer\" class=\"comics-chapters__item\" data-v-9a7b0fc8=\"\"><div style=\"flex: 1;\" data-v-9a7b0fc8=\"\"><span data-v-9a7b0fc8=\"\">566我徐缺舍己为人！</span></div></a>","link":"https://cn.baozimh.com/user/page_direct?comic_id=zuiqiangfantaoluxitong-chuyingshe&section_slot=0&chapter_slot=570","retrieved":1646533274496},{"title":"565修罗众","contents":"<a href=\"/user/page_direct?comic_id=zuiqiangfantaoluxitong-chuyingshe&amp;section_slot=0&amp;chapter_slot=569\" rel=\"noreferrer\" class=\"comics-chapters__item\" data-v-9a7b0fc8=\"\"><div style=\"flex: 1;\" data-v-9a7b0fc8=\"\"><span data-v-9a7b0fc8=\"\">565修罗众</span></div></a>","link":"https://cn.baozimh.com/user/page_direct?comic_id=zuiqiangfantaoluxitong-chuyingshe&section_slot=0&chapter_slot=569","retrieved":1646361155594},{"title":"564噪音攻击","contents":"<a href=\"/user/page_direct?comic_id=zuiqiangfantaoluxitong-chuyingshe&amp;section_slot=0&amp;chapter_slot=568\" rel=\"noreferrer\" class=\"comics-chapters__item\" data-v-9a7b0fc8=\"\"><div style=\"flex: 1;\" data-v-9a7b0fc8=\"\"><span data-v-9a7b0fc8=\"\">564噪音攻击</span></div></a>","link":"https://cn.baozimh.com/user/page_direct?comic_id=zuiqiangfantaoluxitong-chuyingshe&section_slot=0&chapter_slot=568","retrieved":1646188065374},{"title":"563独自前行","contents":"<a href=\"/user/page_direct?comic_id=zuiqiangfantaoluxitong-chuyingshe&amp;section_slot=0&amp;chapter_slot=567\" rel=\"noreferrer\" class=\"comics-chapters__item\" data-v-9a7b0fc8=\"\"><div style=\"flex: 1;\" data-v-9a7b0fc8=\"\"><span data-v-9a7b0fc8=\"\">563独自前行</span></div></a>","link":"https://cn.baozimh.com/user/page_direct?comic_id=zuiqiangfantaoluxitong-chuyingshe&section_slot=0&chapter_slot=567","retrieved":1646188065376},{"title":"562重逢","contents":"<a href=\"/user/page_direct?comic_id=zuiqiangfantaoluxitong-chuyingshe&amp;section_slot=0&amp;chapter_slot=566\" rel=\"noreferrer\" class=\"comics-chapters__item\" data-v-9a7b0fc8=\"\"><div style=\"flex: 1;\" data-v-9a7b0fc8=\"\"><span data-v-9a7b0fc8=\"\">562重逢</span></div></a>","link":"https://cn.baozimh.com/user/page_direct?comic_id=zuiqiangfantaoluxitong-chuyingshe&section_slot=0&chapter_slot=566","retrieved":1646188065378},{"title":"561天门追兵","contents":"<a href=\"/user/page_direct?comic_id=zuiqiangfantaoluxitong-chuyingshe&amp;section_slot=0&amp;chapter_slot=565\" rel=\"noreferrer\" class=\"comics-chapters__item\" data-v-9a7b0fc8=\"\"><div style=\"flex: 1;\" data-v-9a7b0fc8=\"\"><span data-v-9a7b0fc8=\"\">561天门追兵</span></div></a>","link":"https://cn.baozimh.com/user/page_direct?comic_id=zuiqiangfantaoluxitong-chuyingshe&section_slot=0&chapter_slot=565","retrieved":1645841319807},{"title":"560传播法决","contents":"<a href=\"/user/page_direct?comic_id=zuiqiangfantaoluxitong-chuyingshe&amp;section_slot=0&amp;chapter_slot=564\" rel=\"noreferrer\" class=\"comics-chapters__item\" data-v-9a7b0fc8=\"\"><div style=\"flex: 1;\" data-v-9a7b0fc8=\"\"><span data-v-9a7b0fc8=\"\">560传播法决</span></div></a>","link":"https://cn.baozimh.com/user/page_direct?comic_id=zuiqiangfantaoluxitong-chuyingshe&section_slot=0&chapter_slot=564","retrieved":1645841319807},{"title":"559镇压之魂","contents":"<a href=\"/user/page_direct?comic_id=zuiqiangfantaoluxitong-chuyingshe&amp;section_slot=0&amp;chapter_slot=563\" rel=\"noreferrer\" class=\"comics-chapters__item\" data-v-9a7b0fc8=\"\"><div style=\"flex: 1;\" data-v-9a7b0fc8=\"\"><span data-v-9a7b0fc8=\"\">559镇压之魂</span></div></a>","link":"https://cn.baozimh.com/user/page_direct?comic_id=zuiqiangfantaoluxitong-chuyingshe&section_slot=0&chapter_slot=563","retrieved":1645495794213},{"title":"558神秘洞穴","contents":"<a href=\"/user/page_direct?comic_id=zuiqiangfantaoluxitong-chuyingshe&amp;section_slot=0&amp;chapter_slot=562\" rel=\"noreferrer\" class=\"comics-chapters__item\" data-v-9a7b0fc8=\"\"><div style=\"flex: 1;\" data-v-9a7b0fc8=\"\"><span data-v-9a7b0fc8=\"\">558神秘洞穴</span></div></a>","link":"https://cn.baozimh.com/user/page_direct?comic_id=zuiqiangfantaoluxitong-chuyingshe&section_slot=0&chapter_slot=562","retrieved":1645495794214},{"title":"557回首掏","contents":"<a href=\"/user/page_direct?comic_id=zuiqiangfantaoluxitong-chuyingshe&amp;section_slot=0&amp;chapter_slot=561\" rel=\"noreferrer\" class=\"comics-chapters__item\" data-v-9a7b0fc8=\"\"><div style=\"flex: 1;\" data-v-9a7b0fc8=\"\"><span data-v-9a7b0fc8=\"\">557回首掏</span></div></a>","link":"https://cn.baozimh.com/user/page_direct?comic_id=zuiqiangfantaoluxitong-chuyingshe&section_slot=0&chapter_slot=561","retrieved":1645236632051},{"title":"556爱你的形状","contents":"<a href=\"/user/page_direct?comic_id=zuiqiangfantaoluxitong-chuyingshe&amp;section_slot=0&amp;chapter_slot=560\" rel=\"noreferrer\" class=\"comics-chapters__item\" data-v-9a7b0fc8=\"\"><div style=\"flex: 1;\" data-v-9a7b0fc8=\"\"><span data-v-9a7b0fc8=\"\">556爱你的形状</span></div></a>","link":"https://cn.baozimh.com/user/page_direct?comic_id=zuiqiangfantaoluxitong-chuyingshe&section_slot=0&chapter_slot=560","retrieved":1645104899582},{"title":"555苦肉计","contents":"<a href=\"/user/page_direct?comic_id=zuiqiangfantaoluxitong-chuyingshe&amp;section_slot=0&amp;chapter_slot=559\" rel=\"noreferrer\" class=\"comics-chapters__item\" data-v-9a7b0fc8=\"\"><div style=\"flex: 1;\" data-v-9a7b0fc8=\"\"><span data-v-9a7b0fc8=\"\">555苦肉计</span></div></a>","link":"https://cn.baozimh.com/user/page_direct?comic_id=zuiqiangfantaoluxitong-chuyingshe&section_slot=0&chapter_slot=559","retrieved":1644845715611},{"title":"554无法传达的思念","contents":"<a href=\"/user/page_direct?comic_id=zuiqiangfantaoluxitong-chuyingshe&amp;section_slot=0&amp;chapter_slot=558\" rel=\"noreferrer\" class=\"comics-chapters__item\" data-v-9a7b0fc8=\"\"><div style=\"flex: 1;\" data-v-9a7b0fc8=\"\"><span data-v-9a7b0fc8=\"\">554无法传达的思念</span></div></a>","link":"https://cn.baozimh.com/user/page_direct?comic_id=zuiqiangfantaoluxitong-chuyingshe&section_slot=0&chapter_slot=558","retrieved":1644845715611},{"title":"553仙王的实力","contents":"<a href=\"/user/page_direct?comic_id=zuiqiangfantaoluxitong-chuyingshe&amp;section_slot=0&amp;chapter_slot=557\" rel=\"noreferrer\" class=\"comics-chapters__item\" data-v-9a7b0fc8=\"\"><div style=\"flex: 1;\" data-v-9a7b0fc8=\"\"><span data-v-9a7b0fc8=\"\">553仙王的实力</span></div></a>","link":"https://cn.baozimh.com/user/page_direct?comic_id=zuiqiangfantaoluxitong-chuyingshe&section_slot=0&chapter_slot=557","retrieved":1644545507346},{"title":"552挟持","contents":"<a href=\"/user/page_direct?comic_id=zuiqiangfantaoluxitong-chuyingshe&amp;section_slot=0&amp;chapter_slot=556\" rel=\"noreferrer\" class=\"comics-chapters__item\" data-v-9a7b0fc8=\"\"><div style=\"flex: 1;\" data-v-9a7b0fc8=\"\"><span data-v-9a7b0fc8=\"\">552挟持</span></div></a>","link":"https://cn.baozimh.com/user/page_direct?comic_id=zuiqiangfantaoluxitong-chuyingshe&section_slot=0&chapter_slot=556","retrieved":1644500816506},{"title":"551鹤城风云","contents":"<a href=\"/user/page_direct?comic_id=zuiqiangfantaoluxitong-chuyingshe&amp;section_slot=0&amp;chapter_slot=555\" rel=\"noreferrer\" class=\"comics-chapters__item\" data-v-9a7b0fc8=\"\"><div style=\"flex: 1;\" data-v-9a7b0fc8=\"\"><span data-v-9a7b0fc8=\"\">551鹤城风云</span></div></a>","link":"https://cn.baozimh.com/user/page_direct?comic_id=zuiqiangfantaoluxitong-chuyingshe&section_slot=0&chapter_slot=555","retrieved":1644500816509},{"title":"550羽柔仙子","contents":"<a href=\"/user/page_direct?comic_id=zuiqiangfantaoluxitong-chuyingshe&amp;section_slot=0&amp;chapter_slot=554\" rel=\"noreferrer\" class=\"comics-chapters__item\" data-v-9a7b0fc8=\"\"><div style=\"flex: 1;\" data-v-9a7b0fc8=\"\"><span data-v-9a7b0fc8=\"\">550羽柔仙子</span></div></a>","link":"https://cn.baozimh.com/user/page_direct?comic_id=zuiqiangfantaoluxitong-chuyingshe&section_slot=0&chapter_slot=554","retrieved":1644114275804},{"title":"549正气封魔经","contents":"<a href=\"/user/page_direct?comic_id=zuiqiangfantaoluxitong-chuyingshe&amp;section_slot=0&amp;chapter_slot=553\" rel=\"noreferrer\" class=\"comics-chapters__item\" data-v-9a7b0fc8=\"\"><div style=\"flex: 1;\" data-v-9a7b0fc8=\"\"><span data-v-9a7b0fc8=\"\">549正气封魔经</span></div></a>","link":"https://cn.baozimh.com/user/page_direct?comic_id=zuiqiangfantaoluxitong-chuyingshe&section_slot=0&chapter_slot=553","retrieved":1644026074352},{"title":"548苏醒","contents":"<a href=\"/user/page_direct?comic_id=zuiqiangfantaoluxitong-chuyingshe&amp;section_slot=0&amp;chapter_slot=552\" rel=\"noreferrer\" class=\"comics-chapters__item\" data-v-9a7b0fc8=\"\"><div style=\"flex: 1;\" data-v-9a7b0fc8=\"\"><span data-v-9a7b0fc8=\"\">548苏醒</span></div></a>","link":"https://cn.baozimh.com/user/page_direct?comic_id=zuiqiangfantaoluxitong-chuyingshe&section_slot=0&chapter_slot=552","retrieved":1643939922716},{"title":"547一己之力","contents":"<a href=\"/user/page_direct?comic_id=zuiqiangfantaoluxitong-chuyingshe&amp;section_slot=0&amp;chapter_slot=551\" rel=\"noreferrer\" class=\"comics-chapters__item\" data-v-9a7b0fc8=\"\"><div style=\"flex: 1;\" data-v-9a7b0fc8=\"\"><span data-v-9a7b0fc8=\"\">547一己之力</span></div></a>","link":"https://cn.baozimh.com/user/page_direct?comic_id=zuiqiangfantaoluxitong-chuyingshe&section_slot=0&chapter_slot=551","retrieved":1643853975416},{"title":"546爆杀","contents":"<a href=\"/user/page_direct?comic_id=zuiqiangfantaoluxitong-chuyingshe&amp;section_slot=0&amp;chapter_slot=550\" rel=\"noreferrer\" class=\"comics-chapters__item\" data-v-9a7b0fc8=\"\"><div style=\"flex: 1;\" data-v-9a7b0fc8=\"\"><span data-v-9a7b0fc8=\"\">546爆杀</span></div></a>","link":"https://cn.baozimh.com/user/page_direct?comic_id=zuiqiangfantaoluxitong-chuyingshe&section_slot=0&chapter_slot=550","retrieved":1643767785165},{"title":"544疯魔","contents":"<a href=\"/user/page_direct?comic_id=zuiqiangfantaoluxitong-chuyingshe&amp;section_slot=0&amp;chapter_slot=549\" rel=\"noreferrer\" class=\"comics-chapters__item\" data-v-9a7b0fc8=\"\"><div style=\"flex: 1;\" data-v-9a7b0fc8=\"\"><span data-v-9a7b0fc8=\"\">544疯魔</span></div></a>","link":"https://cn.baozimh.com/user/page_direct?comic_id=zuiqiangfantaoluxitong-chuyingshe&section_slot=0&chapter_slot=549","retrieved":1643681535117},{"title":"544万法归一","contents":"<a href=\"/user/page_direct?comic_id=zuiqiangfantaoluxitong-chuyingshe&amp;section_slot=0&amp;chapter_slot=548\" rel=\"noreferrer\" class=\"comics-chapters__item\" data-v-9a7b0fc8=\"\"><div style=\"flex: 1;\" data-v-9a7b0fc8=\"\"><span data-v-9a7b0fc8=\"\">544万法归一</span></div></a>","link":"https://cn.baozimh.com/user/page_direct?comic_id=zuiqiangfantaoluxitong-chuyingshe&section_slot=0&chapter_slot=548","retrieved":1643594814658}]}